gifanimus/__init__.py
gifanimus-0.12.dist-info/licenses/LICENSE
gifanimus-0.12.dist-info/WHEEL
gifanimus-0.12.dist-info/METADATA
gifanimus-0.12.dist-info/RECORD
