Metadata-Version: 2.4
Name: gifanimus
Version: 0.12
Summary: A Simple Gif Animation Window, By: Fibo Metavinci
Author-email: Fibo Metavinci <pszdw-75nat-5227i-bha5s-y7lai-pebdq-o2agp-3xho4-hd6z6-emxrd-nqe@dmail.ai>
License-File: LICENSE
Requires-Dist: pillow>=11.1.0
Requires-Dist: certifi>=2025.4.26
Requires-Dist: charset-normalizer>=3.4.2
Requires-Dist: docutils>=0.21.2
Requires-Dist: idna>=3.10
Requires-Dist: tomli_w>=1.2.0
Requires-Dist: urllib3>=2.4.0
Project-URL: Home, https://github.com/inviti8/gifanimus
